hugginglens/__init__.py
hugginglens/hook_points.py
hugginglens/hooked_transformer.py
hugginglens-0.1.0.dist-info/LICENSE
hugginglens-0.1.0.dist-info/METADATA
hugginglens-0.1.0.dist-info/WHEEL
hugginglens-0.1.0.dist-info/RECORD
