Metadata-Version: 2.1
Name: hugginglens
Version: 0.1.0
Summary: 
Author: Jannik Brinkmann
Author-email: contact.jannikbrinkmann@gmail.com
Requires-Python: >=3.10,<3.13
Classifier: Programming Language :: Python :: 3
Classifier: Programming Language :: Python :: 3.10
Classifier: Programming Language :: Python :: 3.11
Classifier: Programming Language :: Python :: 3.12
Requires-Dist: accelerate (>=0.24.1,<0.25.0)
Requires-Dist: numpy (>=1.26.1,<2.0.0)
Requires-Dist: torch (>=2.1.0,<3.0.0)
Requires-Dist: transformer-lens (>=1.9.1,<2.0.0)
Requires-Dist: transformers (>=4.35.0,<5.0.0)
